package_phonecode/__init__.py
package_phonecode/apps.py
package_phonecode/data.py
package_phonecode/forms.py
package_phonecode/urls.py
package_phonecode/views.py
package_phonecode/templates/package_phonecode/index.html
package_phonecode_pays-0.5.0.dist-info/licenses/LICENSE
test1/__init__.py
test1/asgi.py
test1/settings.py
test1/urls.py
test1/wsgi.py
package_phonecode_pays-0.5.0.dist-info/METADATA
package_phonecode_pays-0.5.0.dist-info/WHEEL
package_phonecode_pays-0.5.0.dist-info/top_level.txt
package_phonecode_pays-0.5.0.dist-info/RECORD
