Metadata-Version: 2.4
Name: package_phonecode_pays
Version: 0.5.0
Summary: Package Django pour obtenir l’indicatif téléphonique selon le pays
Author: ParfaiteSekongo
Author-email: p88971582@gmail.com
License: MIT
Classifier: Framework :: Django
Classifier: Programming Language :: Python :: 3
License-File: LICENSE
Requires-Dist: django>=3.2
Dynamic: author
Dynamic: author-email
Dynamic: classifier
Dynamic: description
Dynamic: description-content-type
Dynamic: license
Dynamic: license-file
Dynamic: requires-dist
Dynamic: summary
